[
  {
    "ContainingType": "ApiFiscalizador.Controllers.ArchivoController",
    "Method": "ObtenerArchivos",
    "RelativePath": "api/Archivos/ObtenerArchivos",
    "HttpMethod": "GET",
    "IsController": true,
    "Order": 0,
    "Parameters": [],
    "ReturnTypes": [
      {
        "Type": "System.Collections.Generic.List\u00601[[ApiFiscalizador.Models.Archivo, ApiFiscalizador, Version=1.0.0.0, Culture=neutral, PublicKeyToken=null]]",
        "MediaTypes": [
          "text/plain",
          "application/json",
          "text/json"
        ],
        "StatusCode": 200
      }
    ]
  },
  {
    "ContainingType": "ApiFiscalizador.Controllers.InstitucionController",
    "Method": "ObtenerInstituciones",
    "RelativePath": "api/Institucion/ObtenerInstituciones",
    "HttpMethod": "GET",
    "IsController": true,
    "Order": 0,
    "Parameters": [],
    "ReturnTypes": [
      {
        "Type": "System.Collections.Generic.List\u00601[[ApiFiscalizador.Models.Institucion, ApiFiscalizador, Version=1.0.0.0, Culture=neutral, PublicKeyToken=null]]",
        "MediaTypes": [
          "text/plain",
          "application/json",
          "text/json"
        ],
        "StatusCode": 200
      }
    ]
  },
  {
    "ContainingType": "ApiFiscalizador.Controllers.PermisoRolController",
    "Method": "ObtenerPermisoxRol",
    "RelativePath": "api/PermisoRol/ObtenerPermisoxRol",
    "HttpMethod": "GET",
    "IsController": true,
    "Order": 0,
    "Parameters": [],
    "ReturnTypes": [
      {
        "Type": "System.Collections.Generic.List\u00601[[ApiFiscalizador.Models.RolPermiso, ApiFiscalizador, Version=1.0.0.0, Culture=neutral, PublicKeyToken=null]]",
        "MediaTypes": [
          "text/plain",
          "application/json",
          "text/json"
        ],
        "StatusCode": 200
      }
    ]
  },
  {
    "ContainingType": "ApiFiscalizador.Controllers.PermisoController",
    "Method": "ObtenerPermisos",
    "RelativePath": "api/Permisos/ObtenerPermisos",
    "HttpMethod": "GET",
    "IsController": true,
    "Order": 0,
    "Parameters": [],
    "ReturnTypes": [
      {
        "Type": "System.Collections.Generic.List\u00601[[ApiFiscalizador.Models.Permiso, ApiFiscalizador, Version=1.0.0.0, Culture=neutral, PublicKeyToken=null]]",
        "MediaTypes": [
          "text/plain",
          "application/json",
          "text/json"
        ],
        "StatusCode": 200
      }
    ]
  },
  {
    "ContainingType": "ApiFiscalizador.Controllers.ProyectoController",
    "Method": "ObtenerProyectos",
    "RelativePath": "api/Proyecto/ObtenerProyectos",
    "HttpMethod": "GET",
    "IsController": true,
    "Order": 0,
    "Parameters": [],
    "ReturnTypes": [
      {
        "Type": "System.Collections.Generic.List\u00601[[ApiFiscalizador.Models.Proyecto, ApiFiscalizador, Version=1.0.0.0, Culture=neutral, PublicKeyToken=null]]",
        "MediaTypes": [
          "text/plain",
          "application/json",
          "text/json"
        ],
        "StatusCode": 200
      }
    ]
  },
  {
    "ContainingType": "ApiFiscalizador.Controllers.RendicionController",
    "Method": "ObtenerRendicion",
    "RelativePath": "api/Rendicion/ObtenerRendicion",
    "HttpMethod": "GET",
    "IsController": true,
    "Order": 0,
    "Parameters": [],
    "ReturnTypes": [
      {
        "Type": "System.Collections.Generic.List\u00601[[ApiFiscalizador.Models.Rendicion, ApiFiscalizador, Version=1.0.0.0, Culture=neutral, PublicKeyToken=null]]",
        "MediaTypes": [
          "text/plain",
          "application/json",
          "text/json"
        ],
        "StatusCode": 200
      }
    ]
  },
  {
    "ContainingType": "ApiFiscalizador.Controllers.RolController",
    "Method": "ObtenerRoles",
    "RelativePath": "api/Rol/ObtenerRoles",
    "HttpMethod": "GET",
    "IsController": true,
    "Order": 0,
    "Parameters": [],
    "ReturnTypes": [
      {
        "Type": "System.Collections.Generic.List\u00601[[ApiFiscalizador.Models.Rol, ApiFiscalizador, Version=1.0.0.0, Culture=neutral, PublicKeyToken=null]]",
        "MediaTypes": [
          "text/plain",
          "application/json",
          "text/json"
        ],
        "StatusCode": 200
      }
    ]
  },
  {
    "ContainingType": "ApiFiscalizador.Controllers.UsuarioController",
    "Method": "ObtenerUsuarios",
    "RelativePath": "api/Usuario/ObtenerUsuarios",
    "HttpMethod": "GET",
    "IsController": true,
    "Order": 0,
    "Parameters": [],
    "ReturnTypes": [
      {
        "Type": "System.Collections.Generic.List\u00601[[ApiFiscalizador.Models.Usuario, ApiFiscalizador, Version=1.0.0.0, Culture=neutral, PublicKeyToken=null]]",
        "MediaTypes": [
          "text/plain",
          "application/json",
          "text/json"
        ],
        "StatusCode": 200
      }
    ]
  },
  {
    "ContainingType": "ApiFiscalizador.Controllers.UsuarioRolController",
    "Method": "ObtenerRolexUsuario",
    "RelativePath": "api/UsuarioRol/ObtenerRolexUsuario",
    "HttpMethod": "GET",
    "IsController": true,
    "Order": 0,
    "Parameters": [],
    "ReturnTypes": [
      {
        "Type": "System.Collections.Generic.List\u00601[[ApiFiscalizador.Models.UsuarioRol, ApiFiscalizador, Version=1.0.0.0, Culture=neutral, PublicKeyToken=null]]",
        "MediaTypes": [
          "text/plain",
          "application/json",
          "text/json"
        ],
        "StatusCode": 200
      }
    ]
  }
]